{
  "done": [
    {
      "source": "Bavaria.pdf",
      "page": 1
    },
    {
      "source": "Bavaria.pdf",
      "page": 2
    },
    {
      "source": "Bavaria.pdf",
      "page": 3
    },
    {
      "source": "Bavaria.pdf",
      "page": 4
    },
    {
      "source": "Bavaria.pdf",
      "page": 5
    },
    {
      "source": "Bavaria.pdf",
      "page": 6
    },
    {
      "source": "Bavaria.pdf",
      "page": 7
    },
    {
      "source": "Bavaria.pdf",
      "page": 8
    },
    {
      "source": "Bavaria.pdf",
      "page": 9
    },
    {
      "source": "Bavaria.pdf",
      "page": 10
    },
    {
      "source": "Bavaria.pdf",
      "page": 11
    },
    {
      "source": "Bavaria.pdf",
      "page": 12
    },
    {
      "source": "Bavaria.pdf",
      "page": 13
    },
    {
      "source": "Bavaria.pdf",
      "page": 14
    },
    {
      "source": "Bavaria.pdf",
      "page": 15
    },
    {
      "source": "Bavaria.pdf",
      "page": 16
    },
    {
      "source": "Bavaria.pdf",
      "page": 17
    },
    {
      "source": "Bavaria.pdf",
      "page": 18
    },
    {
      "source": "Bavaria.pdf",
      "page": 19
    },
    {
      "source": "Bavaria.pdf",
      "page": 20
    },
    {
      "source": "Bavaria.pdf",
      "page": 21
    },
    {
      "source": "Bavaria.pdf",
      "page": 22
    },
    {
      "source": "Bavaria.pdf",
      "page": 23
    },
    {
      "source": "Bavaria.pdf",
      "page": 24
    },
    {
      "source": "Bavaria.pdf",
      "page": 25
    },
    {
      "source": "Bavaria.pdf",
      "page": 26
    },
    {
      "source": "Bavaria.pdf",
      "page": 27
    },
    {
      "source": "Bavaria.pdf",
      "page": 28
    },
    {
      "source": "Bavaria.pdf",
      "page": 29
    },
    {
      "source": "Bavaria.pdf",
      "page": 30
    },
    {
      "source": "Bavaria.pdf",
      "page": 31
    },
    {
      "source": "Bavaria.pdf",
      "page": 32
    },
    {
      "source": "Bavaria.pdf",
      "page": 33
    },
    {
      "source": "Bavaria.pdf",
      "page": 34
    },
    {
      "source": "Bavaria.pdf",
      "page": 35
    },
    {
      "source": "Bavaria.pdf",
      "page": 36
    },
    {
      "source": "Bavaria.pdf",
      "page": 37
    },
    {
      "source": "Bavaria.pdf",
      "page": 38
    }
  ]
}