{
    "Amazon Braket (Amazon)": {
        "website_link": "https://aws.amazon.com/",
        "linkedin_link": "https://www.linkedin.com/company/amazon-web-services/"
    },
    "D-Wave Quantum": {
        "website_link": "https://www.dwavequantum.com/",
        "linkedin_link": "https://www.linkedin.com/company/d-wave-quantum/"
    },
    "Ibm": {
        "website_link": "https://www.ibm.com/",
        "linkedin_link": "https://www.linkedin.com/company/ibm/"
    },
    "Ionq": {
        "website_link": "https://ionq.com/",
        "linkedin_link": "https://www.linkedin.com/company/ionq/"
    },
    "Google Quantum Ai": {
        "website_link": "https://quantumai.google/",
        "linkedin_link": "https://www.linkedin.com/company/google/"
    },
    "Microsoft": {
        "website_link": "https://www.microsoft.com/",
        "linkedin_link": "https://www.linkedin.com/company/microsoft/"
    },
    "Quantum Computing Inc.": {
        "website_link": "https://quantumcomputinginc.com/",
        "linkedin_link": "https://www.linkedin.com/company/quantumcomputinginc/"
    },
    "Rigetti Computing": {
        "website_link": "https://www.rigetti.com/",
        "linkedin_link": "https://www.linkedin.com/company/rigetti-computing/"
    },
    "1Qbit": {
        "website_link": "https://1qbit.com/",
        "linkedin_link": "https://www.linkedin.com/company/1qbit/"
    },
    "Alice & Bob": {
        "website_link": "https://alice-bob.com/",
        "linkedin_link": "https://www.linkedin.com/company/alice-and-bob/"
    },
    "Alpine Quantum Technologies (Aqt)": {
        "website_link": "https://www.aqt.eu/",
        "linkedin_link": "https://www.linkedin.com/company/alpine-quantum-technologies-gmbh/"
    },
    "Anyon Systems": {
        "website_link": "https://anyonsys.com/",
        "linkedin_link": "https://www.linkedin.com/company/anyon-systems-inc-/"
    },
    "Atom Computing": {
        "website_link": "https://atom-computing.com/",
        "linkedin_link": "https://www.linkedin.com/company/atom-computing/"
    },
    "Bluequbit": {
        "website_link": "https://www.bluequbit.io/",
        "linkedin_link": "https://www.linkedin.com/company/bluequbit/"
    },
    "Bosonq Psi": {
        "website_link": "https://www.bqpsim.com/",
        "linkedin_link": "https://www.linkedin.com/company/bqp-sim/"
    },
    "Classiq": {
        "website_link": "https://www.classiq.io/",
        "linkedin_link": "https://www.linkedin.com/company/classiq/"
    },
    "Crypto Quantique": {
        "website_link": "https://www.cryptoquantique.com/",
        "linkedin_link": "https://www.linkedin.com/company/crypto-quantique/"
    },
    "Delft Circuits": {
        "website_link": "https://delft-circuits.com/",
        "linkedin_link": "https://www.linkedin.com/company/delft-circuits/"
    },
    "Diraq": {
        "website_link": "https://diraq.com/",
        "linkedin_link": "https://www.linkedin.com/company/diraq/"
    },
    "Eeroq": {
        "website_link": "https://eeroq.com/",
        "linkedin_link": "https://www.linkedin.com/company/eeroq/"
    },
    "Eleqtron": {
        "website_link": "https://eleqtron.com/",
        "linkedin_link": "https://www.linkedin.com/company/eleqtron/"
    },
    "Evolutionq": {
        "website_link": "https://www.evolutionq.com/",
        "linkedin_link": "https://www.linkedin.com/company/evolutionq/"
    },
    "Horizon Quantum Computing": {
        "website_link": "https://www.horizonquantum.com/",
        "linkedin_link": "https://www.linkedin.com/company/horizon-quantum-computing/"
    },
    "Hqs Quantum Simulations": {
        "website_link": "https://quantumsimulations.de/",
        "linkedin_link": "https://www.linkedin.com/company/hqs-quantum-simulations/"
    },
    "Infinityq": {
        "website_link": "https://www.linkedin.com/company/infinityq/",
        "linkedin_link": "https://www.linkedin.com/company/infinityq/"
    },
    "Infleqtion": {
        "website_link": "https://infleqtion.com/",
        "linkedin_link": "https://www.linkedin.com/company/infq/"
    },
    "Iqm": {
        "website_link": "https://meetiqm.com/",
        "linkedin_link": "https://www.linkedin.com/company/iqm/"
    },
    "Kets Quantum Security": {
        "website_link": "https://kets-quantum.com/",
        "linkedin_link": "https://www.linkedin.com/company/kets-quantum/"
    },
    "Kiutra": {
        "website_link": "https://kiutra.com/",
        "linkedin_link": "https://www.linkedin.com/company/kiutra/"
    },
    "Multiverse Computing": {
        "website_link": "https://multiversecomputing.com/",
        "linkedin_link": "https://www.linkedin.com/company/multiversecomputing/"
    },
    "Nord Quantique": {
        "website_link": "https://nordquantique.ca/",
        "linkedin_link": "https://www.linkedin.com/company/nord-quantique/"
    },
    "Orca Computing": {
        "website_link": "https://orcacomputing.com/",
        "linkedin_link": "https://www.linkedin.com/company/orcacomputing/"
    },
    "Oxford Quantum Circuits (Oqc)": {
        "website_link": "https://oqc.tech/",
        "linkedin_link": "https://www.linkedin.com/company/oqc/"
    },
    "Parityqc": {
        "website_link": "https://parityqc.com/",
        "linkedin_link": "https://www.linkedin.com/company/parityqc/"
    },
    "Pasqal": {
        "website_link": "https://www.pasqal.com/",
        "linkedin_link": "https://www.linkedin.com/company/pasqal/"
    },
    "Photonic Inc.": {
        "website_link": "https://photonic.com/",
        "linkedin_link": "https://www.linkedin.com/company/photonic-inc/"
    },
    "Pqshield": {
        "website_link": "https://pqshield.com/",
        "linkedin_link": "https://www.linkedin.com/company/pqshield/"
    },
    "Proteinqure": {
        "website_link": "https://www.proteinqure.com/",
        "linkedin_link": "https://www.linkedin.com/company/proteinqure/"
    },
    "Qaisec": {
        "website_link": "https://qaisec.eu/",
        "linkedin_link": "https://www.linkedin.com/company/qaisec/"
    },
    "Psiquantum": {
        "website_link": "https://www.psiquantum.com/",
        "linkedin_link": "https://www.linkedin.com/company/psiquantum/"
    },
    "Q-Ctrl": {
        "website_link": "https://q-ctrl.com/",
        "linkedin_link": "https://www.linkedin.com/company/q-ctrl/"
    },
    "Qc Ware": {
        "website_link": "https://www.qcware.com/",
        "linkedin_link": "https://www.linkedin.com/company/qcware/"
    },
    "Qruise": {
        "website_link": "https://www.qruise.com/",
        "linkedin_link": "https://www.linkedin.com/company/qruise/"
    },
    "Qsimulate": {
        "website_link": "https://qsimulate.com/",
        "linkedin_link": "https://www.linkedin.com/company/qsimulate/"
    },
    "Quandela": {
        "website_link": "https://www.quandela.com/",
        "linkedin_link": "https://www.linkedin.com/company/quandela/"
    },
    "Quantfi": {
        "website_link": "https://www.quantfi.us/",
        "linkedin_link": "https://www.linkedin.com/company/quantfi/"
    },
    "Quantistry": {
        "website_link": "https://www.quantistry.com/",
        "linkedin_link": "https://www.linkedin.com/company/quantistry/"
    },
    "Quantum Base": {
        "website_link": "https://quantumbase.com/",
        "linkedin_link": "https://www.linkedin.com/company/quantum-base/"
    },
    "Quantum Brilliance": {
        "website_link": "https://quantumbrilliance.com/",
        "linkedin_link": "https://www.linkedin.com/company/quantum-brilliance/"
    },
    "Quantum Circuits": {
        "website_link": "https://quantumcircuits.com/",
        "linkedin_link": "https://www.linkedin.com/company/quantum-circuits-inc/"
    },
    "Quantum Dice": {
        "website_link": "https://www.quantum-dice.com/",
        "linkedin_link": "https://www.linkedin.com/company/quantum-dice/"
    },
    "Quantum Machines": {
        "website_link": "https://www.quantum-machines.co/",
        "linkedin_link": "https://www.linkedin.com/company/quantumachines/"
    },
    "Quantum Motion": {
        "website_link": "https://quantummotion.tech/",
        "linkedin_link": "https://www.linkedin.com/company/quantum-motion-tech/"
    },
    "Quantum-South": {
        "website_link": "https://quantum-south.com/",
        "linkedin_link": "https://www.linkedin.com/company/quantum-south/"
    },
    "Quantware": {
        "website_link": "https://www.quantware.com/",
        "linkedin_link": "https://www.linkedin.com/company/quantware/"
    },
    "Qubit Engineering": {
        "website_link": "https://qubitengineering.com/",
        "linkedin_link": "https://www.linkedin.com/company/qubit-engineering-inc/"
    },
    "Qubit Pharmaceuticals": {
        "website_link": "https://www.qubit-pharmaceuticals.com/",
        "linkedin_link": "https://www.linkedin.com/company/qubit-pharmaceuticals/"
    },
    "Quera Computing": {
        "website_link": "https://www.quera.com/",
        "linkedin_link": "https://www.linkedin.com/company/quera-computing-inc/"
    },
    "Quintessencelabs": {
        "website_link": "https://www.quintessencelabs.com/",
        "linkedin_link": "https://www.linkedin.com/company/quintessencelabs/"
    },
    "Quix Quantum": {
        "website_link": "https://www.quixquantum.com/",
        "linkedin_link": "https://www.linkedin.com/company/quix-quantum/"
    },
    "Qunasys": {
        "website_link": "https://qunasys.com/en/",
        "linkedin_link": "https://www.linkedin.com/company/qunasys/"
    },
    "Qunnect": {
        "website_link": "https://www.qunnect.inc/",
        "linkedin_link": "https://www.linkedin.com/company/qunnect/"
    },
    "Qnu Labs": {
        "website_link": "https://www.qnulabs.com/",
        "linkedin_link": "https://www.linkedin.com/company/qunu-labs-pvt-ltd/"
    },
    "Riverlane": {
        "website_link": "https://www.riverlane.com/",
        "linkedin_link": "https://www.linkedin.com/company/riverlane/"
    },
    "Scalinq": {
        "website_link": "https://www.scalinq.com/",
        "linkedin_link": "https://www.linkedin.com/company/scalinq/"
    },
    "Seeqc": {
        "website_link": "https://seeqc.com/",
        "linkedin_link": "https://www.linkedin.com/company/seeqc-us/"
    },
    "Single Quantum": {
        "website_link": "https://www.singlequantum.com/",
        "linkedin_link": "https://www.linkedin.com/company/single-quantum/"
    },
    "Spinq": {
        "website_link": "https://www.spinquanta.com/",
        "linkedin_link": "https://www.linkedin.com/company/spinq-inc/"
    },
    "Silicon Quantum Computing": {
        "website_link": "http://www.sqc.com.au/",
        "linkedin_link": "https://www.linkedin.com/company/silicon-quantum-computing-pty-ltd/"
    },
    "Sparrow Quantum": {
        "website_link": "https://sparrowquantum.com/",
        "linkedin_link": "https://www.linkedin.com/company/sparrow-quantum/"
    },
    "Strangeworks": {
        "website_link": "https://strangeworks.com/",
        "linkedin_link": "https://www.linkedin.com/company/strangeworks/"
    },
    "Terra Quantum": {
        "website_link": "https://terraquantum.swiss/",
        "linkedin_link": "https://www.linkedin.com/company/terra-quantum/"
    },
    "Turing": {
        "website_link": "https://www.turing.com/",
        "linkedin_link": "https://www.linkedin.com/company/turing/"
    },
    "Universal Quantum": {
        "website_link": "https://universalquantum.com/",
        "linkedin_link": "https://www.linkedin.com/company/universal-quantum/"
    },
    "Welinq": {
        "website_link": "https://www.welinq.fr/",
        "linkedin_link": "https://www.linkedin.com/company/welinq/"
    },
    "Xanadu": {
        "website_link": "https://www.xanadu.ai/",
        "linkedin_link": "https://www.linkedin.com/company/xanadu/"
    }, 
    "Quantinuum": {
        "website_link": "https://www.quantinuum.com/",
        "linkedin_link": "https://www.linkedin.com/company/quantinuumqc/"
    },
    "Intel": {
        "website_link": "https://www.intel.com/content/www/us/en/research/quantum-computing.html",
        "linkedin_link": "https://www.linkedin.com/company/intel-corporation/"
    },
    "Fujitsu": {
        "website_link": "https://global.fujitsu/en-global/technology/research/quantum",
        "linkedin_link": "https://www.linkedin.com/company/fujitsu/"
    }, 
    "AIM Photonics": {
        "website_link": "https://www.aimphotonics.com/",
        "linkedin_link": "https://www.linkedin.com/company/aimphotonics/"
    }, 
    "Aeluma": {
        "website_link": "https://www.aeluma.com/",
        "linkedin_link": "https://www.linkedin.com/company/aeluma/"
    }
}