[
  {
    "entity": "Fermi National Accelerator Laboratory",
    "status": "entity",
    "excluded_reason": "Null",
    "category": "research institutes",
    "role_in_text": "publishes quantum computing course",
    "technology_area": "quantum computing",
    "occurrence_sentence": "Fermilab scientists publish quantum computing course for high school students",
    "source_document": "https://thequantuminsider.com/2020/06/09/fermilab-scientists-publish-quantum-computing-course-for-high-school-students",
    "page": 1,
    "confidence": "high"
  },
  {
    "entity": "Fermi National Accelerator Laboratory",
    "status": "entity",
    "excluded_reason": "Null",
    "category": "research institutes",
    "role_in_text": "publish quantum computing course",
    "technology_area": "quantum computing",
    "occurrence_sentence": "Fermilab scientists publish quantum computing course for high school students",
    "source_document": "https://thequantuminsider.com/2020/06/09/fermilab-scientists-publish-quantum-computing-course-for-high-school-students",
    "page": 2,
    "confidence": "high"
  },
  {
    "entity": "Fermi National Accelerator Laboratory",
    "status": "entity",
    "excluded_reason": "Null",
    "category": "research institutes",
    "role_in_text": "publishes quantum computing course",
    "technology_area": "quantum computing",
    "occurrence_sentence": "Fermilab scientists publish quantum computing course for high school students",
    "source_document": "https://thequantuminsider.com/2020/06/09/fermilab-scientists-publish-quantum-computing-course-for-high-school-students",
    "page": 3,
    "confidence": "high"
  },
  {
    "entity": "Fermi National Accelerator Laboratory",
    "status": "entity",
    "excluded_reason": "Null",
    "category": "research institutes",
    "role_in_text": "publishes quantum computing course",
    "technology_area": "quantum computing",
    "occurrence_sentence": "Fermilab scientists publish quantum computing course for high school students",
    "source_document": "https://thequantuminsider.com/2020/06/09/fermilab-scientists-publish-quantum-computing-course-for-high-school-students",
    "page": 4,
    "confidence": "high"
  },
  {
    "entity": "Fermilab",
    "status": "entity",
    "excluded_reason": "Null",
    "category": "research institutes",
    "role_in_text": "publishes quantum computing course",
    "technology_area": "quantum computing",
    "occurrence_sentence": "Fermilab scientists publish quantum computing course for high school students",
    "source_document": "https://thequantuminsider.com/2020/06/09/fermilab-scientists-publish-quantum-computing-course-for-high-school-students",
    "page": 5,
    "confidence": "high"
  },
  {
    "entity": "Fermi National Accelerator Laboratory",
    "status": "entity",
    "excluded_reason": "Null",
    "category": "research institutes",
    "role_in_text": "Fermilab scientists publish a quantum computing course for high school students",
    "technology_area": "quantum computing",
    "occurrence_sentence": "Fermilab scientists publish quantum computing course for high school students",
    "source_document": "https://thequantuminsider.com/2020/06/09/fermilab-scientists-publish-quantum-computing-course-for-high-school-students",
    "page": 6,
    "confidence": "high"
  },
  {
    "entity": "Fermi National Accelerator Laboratory",
    "status": "entity",
    "excluded_reason": "Null",
    "category": "research institutes",
    "role_in_text": "publish quantum computing course",
    "technology_area": "quantum computing",
    "occurrence_sentence": "Fermilab scientists publish quantum computing course for high school students",
    "source_document": "https://thequantuminsider.com/2020/06/09/fermilab-scientists-publish-quantum-computing-course-for-high-school-students",
    "page": 7,
    "confidence": "high"
  },
  {
    "entity": "Fermilab",
    "status": "entity",
    "excluded_reason": "Null",
    "category": "research institutes",
    "role_in_text": "publishes quantum computing course",
    "technology_area": "quantum computing",
    "occurrence_sentence": "Fermilab scientists publish quantum computing course for high school students",
    "source_document": "https://thequantuminsider.com/2020/06/09/fermilab-scientists-publish-quantum-computing-course-for-high-school-students",
    "page": 8,
    "confidence": "high"
  },
  {
    "entity": "Fermi National Accelerator Laboratory",
    "status": "entity",
    "excluded_reason": "Null",
    "category": "research institutes",
    "role_in_text": "publishes a quantum computing course",
    "technology_area": "quantum computing",
    "occurrence_sentence": "Fermilab scientists publish quantum computing course for high school students",
    "source_document": "https://thequantuminsider.com/2020/06/09/fermilab-scientists-publish-quantum-computing-course-for-high-school-students",
    "page": 9,
    "confidence": "high"
  },
  {
    "entity": "Fermi National Accelerator Laboratory",
    "status": "entity",
    "excluded_reason": "Null",
    "category": "research institutes",
    "role_in_text": "publish quantum computing course",
    "technology_area": "quantum computing",
    "occurrence_sentence": "Fermilab scientists publish quantum computing course for high school students",
    "source_document": "https://thequantuminsider.com/2020/06/09/fermilab-scientists-publish-quantum-computing-course-for-high-school-students",
    "page": 10,
    "confidence": "high"
  },
  {
    "entity": "Fermilab",
    "status": "entity",
    "excluded_reason": "Null",
    "category": "research institutes",
    "role_in_text": "publishes a quantum computing course",
    "technology_area": "quantum computing",
    "occurrence_sentence": "Fermilab Scientists Publish Quantum Computing Course for High School Students",
    "source_document": "https://thequantuminsider.com/2020/06/09/fermilab-scientists-publish-quantum-computing-course-for-high-school-students",
    "page": 11,
    "confidence": "high"
  },
  {
    "entity": "Ciaran Hughes",
    "status": "entity",
    "excluded_reason": "Null",
    "category": "individual",
    "role_in_text": "author of the article",
    "technology_area": "quantum computing",
    "occurrence_sentence": "Ciaran Hughes",
    "source_document": "https://thequantuminsider.com/2020/06/09/fermilab-scientists-publish-quantum-computing-course-for-high-school-students",
    "page": 11
  },
  {
    "entity": "Fermilab",
    "status": "entity",
    "excluded_reason": "Null",
    "category": "research institutes",
    "role_in_text": "world leader in quantum physics",
    "technology_area": "quantum computing",
    "occurrence_sentence": "Fermilab regularly makes fundamental science discoveries and is a world leader in quantum physics.",
    "source_document": "https://thequantuminsider.com/2020/06/09/fermilab-scientists-publish-quantum-computing-course-for-high-school-students",
    "page": 12,
    "confidence": "high"
  },
  {
    "entity": "Fermilab Quantum Institute",
    "status": "entity",
    "excluded_reason": "Null",
    "category": "research institutes",
    "role_in_text": "conducts world-class research at the leading edge of quantum computing and information science",
    "technology_area": "quantum computing",
    "occurrence_sentence": "In 2019, it launched the Fermilab Quantum Institute, which",
    "source_document": "https://thequantuminsider.com/2020/06/09/fermilab-scientists-publish-quantum-computing-course-for-high-school-students",
    "page": 12
  },
  {
    "entity": "Fermilab",
    "status": "entity",
    "excluded_reason": "Null",
    "category": "research institutes",
    "role_in_text": "world leader in quantum physics",
    "technology_area": "quantum computing",
    "occurrence_sentence": "Fermilab regularly makes fundamental science discoveries and is a world leader in quantum physics.",
    "source_document": "https://thequantuminsider.com/2020/06/09/fermilab-scientists-publish-quantum-computing-course-for-high-school-students",
    "page": 13,
    "confidence": "high"
  },
  {
    "entity": "Fermilab Quantum Institute",
    "status": "entity",
    "excluded_reason": "Null",
    "category": "research institutes",
    "role_in_text": "conducts world-class research at the leading edge of quantum computing and information science",
    "technology_area": "quantum computing",
    "occurrence_sentence": "In 2019, it launched the Fermilab Quantum Institute, which",
    "source_document": "https://thequantuminsider.com/2020/06/09/fermilab-scientists-publish-quantum-computing-course-for-high-school-students",
    "page": 13
  },
  {
    "entity": "Anastasia",
    "status": "entity",
    "excluded_reason": "Null",
    "category": "individual",
    "role_in_text": "contributed to the development of the quantum computing course",
    "technology_area": "quantum computing",
    "occurrence_sentence": "During the summer, Anastasia and Ranbel met with us several times a week to discuss the foundations of quantum mechanics, quantum computing and how to best present this information to a high school level audience.",
    "source_document": "https://thequantuminsider.com/2020/06/09/fermilab-scientists-publish-quantum-computing-course-for-high-school-students",
    "page": 14,
    "confidence": "high"
  },
  {
    "entity": "Ranbel",
    "status": "entity",
    "excluded_reason": "Null",
    "category": "individual",
    "role_in_text": "contributed to the development of the quantum computing course",
    "technology_area": "quantum computing",
    "occurrence_sentence": "During the summer",
    "source_document": "https://thequantuminsider.com/2020/06/09/fermilab-scientists-publish-quantum-computing-course-for-high-school-students",
    "page": 14
  },
  {
    "entity": "Fermi National Accelerator Laboratory",
    "status": "entity",
    "excluded_reason": "Null",
    "category": "research institutes",
    "role_in_text": "developed a quantum computing course for high school students",
    "technology_area": "quantum computing",
    "occurrence_sentence": "Fermilab scientists are breaking new ground in both quantum computing research and ensuring the competitiveness of the STEM workforce in the quantum era.",
    "source_document": "https://thequantuminsider.com/2020/06/09/fermilab-scientists-publish-quantum-computing-course-for-high-school-students",
    "page": 15,
    "confidence": "high"
  },
  {
    "entity": "IBM",
    "status": "entity",
    "excluded_reason": "Null",
    "category": "large enterprises",
    "role_in_text": "provides real quantum computers used in the course",
    "technology_area": "quantum computing",
    "occurrence_sentence": "We've heard that the walkthrough exercises that use",
    "source_document": "https://thequantuminsider.com/2020/06/09/fermilab-scientists-publish-quantum-computing-course-for-high-school-students",
    "page": 15
  },
  {
    "entity": "Fermilab",
    "status": "entity",
    "excluded_reason": "Null",
    "category": "research institutes",
    "role_in_text": "Fermilab scientists are breaking new ground in both quantum computing research and ensuring the competitiveness of the STEM workforce in the quantum era.",
    "technology_area": "quantum computing",
    "occurrence_sentence": "With this quantum computing course, Fermilab scientists are breaking new ground in both quantum computing research and ensuring the competitiveness of the STEM workforce in the quantum era.",
    "source_document": "https://thequantuminsider.com/2020/06/09/fermilab-scientists-publish-quantum-computing-course-for-high-school-students",
    "page": 16,
    "confidence": "high"
  },
  {
    "entity": "The American Association of Physics Teachers",
    "status": "entity",
    "excluded_reason": "Null",
    "category": "non-governmental and non-profit organizations",
    "role_in_text": "The American Association of Physics Teachers is excited to",
    "source_document": "https://thequantuminsider.com/2020/06/09/fermilab-scientists-publish-quantum-computing-course-for-high-school-students",
    "page": 16
  },
  {
    "entity": "Fermilab",
    "status": "entity",
    "excluded_reason": "Null",
    "category": "research institutes",
    "role_in_text": "Fermilab scientists publish a quantum computing course for high school students",
    "technology_area": "quantum computing",
    "occurrence_sentence": "Fermilab scientists publish quantum computing course for high school students",
    "source_document": "https://thequantuminsider.com/2020/06/09/fermilab-scientists-publish-quantum-computing-course-for-high-school-students",
    "page": 17,
    "confidence": "high"
  },
  {
    "entity": "Ciaran Hughes",
    "status": "entity",
    "excluded_reason": "Null",
    "category": "individual",
    "role_in_text": "Author of the article",
    "technology_area": "quantum computing",
    "occurrence_sentence": "Ciaran Hughes",
    "source_document": "https://thequantuminsider.com/2020/06/09/fermilab-scientists-publish-quantum-computing-course-for-high-school-students",
    "page": 17
  },
  {
    "entity": "Ciaran Hughes",
    "status": "entity",
    "excluded_reason": "Null",
    "category": "individual",
    "role_in_text": "author or contributor",
    "technology_area": "unknown",
    "occurrence_sentence": "Ciaran Hughes",
    "source_document": "https://thequantuminsider.com/2020/06/09/fermilab-scientists-publish-quantum-computing-course-for-high-school-students",
    "page": 18,
    "confidence": "high"
  },
  {
    "entity": "Quantum Leap",
    "status": "entity",
    "excluded_reason": "Null",
    "category": "small and medium-sized enterprises",
    "role_in_text": "raises funding",
    "technology_area": "quantum computing",
    "occurrence_sentence": "Quantum Leap Raises $230 Million as SPAC Eyes AI And Quantum Targets",
    "source_document": "https://thequantuminsider.com/2020/06/09/fermilab-scientists-publish-quantum-computing-course-for-high-school-students",
    "page": 18
  },
  {
    "entity": "Classiq",
    "status": "entity",
    "excluded_reason": "Null",
    "category": "small and medium-sized enterprises",
    "role_in_text": "Launched a quantum cloud offering in Korea",
    "technology_area": "quantum computing",
    "occurrence_sentence": "Classiq and QAI Launch Quantum Cloud Offering in Korea",
    "source_document": "https://thequantuminsider.com/2020/06/09/fermilab-scientists-publish-quantum-computing-course-for-high-school-students",
    "page": 19,
    "confidence": "high"
  },
  {
    "entity": "QAI",
    "status": "entity",
    "excluded_reason": "Null",
    "category": "small and medium-sized enterprises",
    "role_in_text": "Launched a quantum cloud offering in Korea",
    "technology_area": "quantum computing",
    "occurrence_sentence": "Classiq and QAI Launch Quantum Cloud Offering in Korea",
    "source_document": "https://thequantuminsider.com/2020/06/09/fermilab-scientists-publish-quantum-computing-course-for-high-school-students",
    "page": 19
  },
  {
    "entity": "Matt Swayne",
    "status": "entity",
    "excluded_reason": "Null",
    "category": "individual",
    "role_in_text": "author",
    "technology_area": "quantum computing",
    "occurrence_sentence": "Matt Swayne",
    "source_document": "https://thequantuminsider.com/2020/06/09/fermilab-scientists-publish-quantum-computing-course-for-high-school-students",
    "page": 20,
    "confidence": "high"
  },
  {
    "entity": "Mohib Ur Rehman",
    "status": "entity",
    "excluded_reason": "Null",
    "category": "individual",
    "role_in_text": "author",
    "technology_area": "quantum computing",
    "occurrence_sentence": "Mohib Ur Rehman",
    "source_document": "https://thequantuminsider.com/2020/06/09/fermilab-scientists-publish-quantum-computing-course-for-high-school-students",
    "page": 20
  },
  {
    "entity": "National Security Agency (NSA)",
    "status": "entity",
    "excluded_reason": "Null",
    "category": "national government institutions",
    "role_in_text": "launched the QuantumEAGLe initiative",
    "technology_area": "quantum computing",
    "occurrence_sentence": "NSA Introduces QuantumEAGLe Program to Advance U.S. Quantum Computing",
    "source_document": "https://thequantuminsider.com/2020/06/09/fermilab-scientists-publish-quantum-computing-course-for-high-school-students",
    "page": 21,
    "confidence": "high"
  },
  {
    "entity": "Defense Advanced Research Projects Agency (DARPA)",
    "status": "entity",
    "excluded_reason": "Null",
    "category": "national government institutions",
    "role_in_text": "part of the QuantumEAGLe initiative",
    "technology_area": "quantum computing",
    "occurrence_sentence": "NSA Introduces QuantumEAGLe Program to Advance U.S. Quantum Computing",
    "source_document": "https://thequantuminsider.com/2020/06/09/fermilab-scientists-publish-quantum-computing-course-for-high-school-students",
    "page": 21
  },
  {
    "entity": "National Security Agency (NSA)",
    "status": "entity",
    "excluded_reason": "Null",
    "category": "national government institutions",
    "role_in_text": "Introduces QuantumEAGLe Program",
    "technology_area": "quantum computing",
    "occurrence_sentence": "NSA Introduces QuantumEAGLe Program to Advance U.S. Quantum Computing",
    "source_document": "https://thequantuminsider.com/2020/06/09/fermilab-scientists-publish-quantum-computing-course-for-high-school-students",
    "page": 22,
    "confidence": "high"
  },
  {
    "entity": "Quantum Leap",
    "status": "entity",
    "excluded_reason": "Null",
    "category": "small and medium-sized enterprises",
    "role_in_text": "Raises $230 Million",
    "technology_area": "AI | quantum computing",
    "occurrence_sentence": "Quantum Leap Raises $230 Million as SPAC Eyes AI And Quantum Targets",
    "source_document": "https://thequantuminsider.com/2020/06/09/fermilab-scientists-publish-quantum-computing-course-for-high-school-students",
    "page": 22
  },
  {
    "entity": "The Quantum Insider (TQI)",
    "status": "entity",
    "excluded_reason": "Null",
    "category": "media and cultural institutions",
    "role_in_text": "leading source for the latest quantum technology news",
    "technology_area": "deep tech general",
    "occurrence_sentence": "The Quantum Insider (TQI) is the leading source for the latest quantum technology news, market intelligence, industry analysis, and data covering the global quantum ecosystem.",
    "source_document": "https://thequantuminsider.com/2020/06/09/fermilab-scientists-publish-quantum-computing-course-for-high-school-students",
    "page": 23,
    "confidence": "high"
  },
  {
    "entity": "Quantum Leap",
    "status": "entity",
    "excluded_reason": "Null",
    "category": "small and medium-sized enterprises",
    "role_in_text": "raises $230 million as SPAC eyes AI and quantum targets",
    "technology_area": "quantum computing",
    "source_document": "https://thequantuminsider.com/2020/06/09/fermilab-scientists-publish-quantum-computing-course-for-high-school-students",
    "page": 23
  },
  {
    "entity": "National Security Agency (NSA)",
    "status": "entity",
    "excluded_reason": "Null",
    "category": "national government institutions",
    "role_in_text": "Introduces QuantumEAGLe Program",
    "technology_area": "quantum computing",
    "occurrence_sentence": "NSA Introduces QuantumEAGLe Program to Advance U.S. Quantum Computing",
    "source_document": "https://thequantuminsider.com/2020/06/09/fermilab-scientists-publish-quantum-computing-course-for-high-school-students",
    "page": 24,
    "confidence": "high"
  },
  {
    "entity": "Defense Acquisition University (DevCom)",
    "status": "entity",
    "excluded_reason": "Null",
    "category": "national government institutions",
    "role_in_text": "Launches QuantumEAGLe Initiative",
    "technology_area": "quantum computing",
    "occurrence_sentence": "NSA Introduces QuantumEAGLe Program to Advance U.S. Quantum Computing",
    "source_document": "https://thequantuminsider.com/2020/06/09/fermilab-scientists-publish-quantum-computing-course-for-high-school-students",
    "page": 24
  },
  {
    "entity": "Fermi National Accelerator Laboratory",
    "status": "entity",
    "excluded_reason": "Null",
    "category": "research institutes",
    "role_in_text": "publishes quantum computing course",
    "technology_area": "quantum computing",
    "occurrence_sentence": "Fermilab scientists publish quantum computing course for high school students",
    "source_document": "https://thequantuminsider.com/2020/06/09/fermilab-scientists-publish-quantum-computing-course-for-high-school-students",
    "page": 25,
    "confidence": "high"
  },
  {
    "entity": "Resonance Holdings",
    "status": "entity",
    "excluded_reason": "Null",
    "category": "business support institutions",
    "role_in_text": "project",
    "technology_area": "deep tech general",
    "occurrence_sentence": "Resonance",
    "source_document": "https://thequantuminsider.com/2020/06/09/fermilab-scientists-publish-quantum-computing-course-for-high-school-students",
    "page": 25
  },
  {
    "entity": "The Quantum Insider (TQI)",
    "status": "entity",
    "excluded_reason": "Null",
    "category": "media and cultural institutions",
    "role_in_text": "leading source for quantum technology news, market intelligence, industry analysis, and data covering the global quantum ecosystem",
    "technology_area": "deep tech general",
    "occurrence_sentence": "The Quantum Insider (TQI) is the leading source for quantum technology news, market intelligence, industry analysis, and data covering the global quantum ecosystem.",
    "source_document": "https://thequantuminsider.com/2020/06/09/fermilab-scientists-publish-quantum-computing-course-for-high-school-students",
    "page": 26,
    "confidence": "high"
  },
  {
    "entity": "Resonance Alliance Inc.",
    "status": "entity",
    "excluded_reason": "Null",
    "category": "non-governmental and non-profit organizations",
    "role_in_text": "Publisher of the website",
    "technology_area": "deep tech general",
    "occurrence_sentence": "2026 © Resonance Alliance Inc.",
    "source_document": "https://thequantuminsider.com/2020/06/09/fermilab-scientists-publish-quantum-computing-course-for-high-school-students",
    "page": 27,
    "confidence": "high"
  },
  {
    "entity": "Resonance Holdings",
    "status": "entity",
    "excluded_reason": "Null",
    "category": "non-governmental and non-profit organizations",
    "role_in_text": "Parent organization",
    "technology_area": "deep tech general",
    "occurrence_sentence": "* [ Resonance",
    "source_document": "https://thequantuminsider.com/2020/06/09/fermilab-scientists-publish-quantum-computing-course-for-high-school-students",
    "page": 27
  },
  {
    "entity": "Resonance Alliance Inc.",
    "status": "entity",
    "excluded_reason": "Null",
    "category": "non-governmental and non-profit organizations",
    "role_in_text": "Designed by Resonance",
    "technology_area": "unknown",
    "occurrence_sentence": "2026 © Resonance Alliance Inc. All Rights Reserved Designed by Resonance",
    "source_document": "https://thequantuminsider.com/2020/06/09/fermilab-scientists-publish-quantum-computing-course-for-high-school-students",
    "page": 28,
    "confidence": "medium"
  },
  {
    "entity": "Fermi National Accelerator Laboratory",
    "status": "entity",
    "excluded_reason": "Null",
    "category": "research institutes",
    "role_in_text": "Fermilab scientists publish quantum computing course",
    "technology_area": "quantum computing",
    "occurrence_sentence": "Fermilab scientists publish quantum computing course for high school students",
    "source_document": "https://thequantuminsider.com/2020/06/09/fermilab-scientists-publish-quantum-computing-course-for-high-school-students",
    "page": 29,
    "confidence": "high"
  },
  {
    "entity": "Germany",
    "status": "entity",
    "excluded_reason": "Null",
    "category": "country",
    "role_in_text": "country",
    "technology_area": "unknown",
    "occurrence_sentence": "Deutschland) Ghana (Gaana) Gibraltar Greece (Ελλάδα) Greenland (Kalaallit Nunaat) Grenada Guadeloupe Guam Guatemala Guinea (Guinée) Guinea-Bissau (Guiné Bissau) Guyana Haiti Honduras Hong Kong (香港) Hungary (Magyarország) Iceland (Ísland) India (भारत) Indonesia Iran (‫ایران‬‎) Iraq (‫العراق‬‎) Ireland Israel (‫ישראל‬‎) Italy (Italia) Jamaica Japan (日本) Jordan (‫الأردن‬‎) Kazakhstan (Казахстан) Kenya Kiribati Kosovo Kuwait (‫الكويت‬‎) Kyrgyzstan (Кыргызстан) Laos (ລາວ) Latvia (Latvija) Lebanon (‫لبنان‬‎) Lesotho Liberia Libya (‫ليبيا‬‎) Liechtenstein Lithuania (Lietuva) Luxembourg Macau (澳門) Macedonia",
    "source_document": "https://thequantuminsider.com/2020/06/09/fermilab-scientists-publish-quantum-computing-course-for-high-school-students",
    "page": 30
  },
  {
    "entity": "United Kingdom",
    "status": "entity",
    "excluded_reason": "Null",
    "category": "country",
    "role_in_text": "country",
    "technology_area": "unknown",
    "occurrence_sentence": "Country* Select Country United Kingdom United States",
    "source_document": "https://thequantuminsider.com/2020/06/09/fermilab-scientists-publish-quantum-computing-course-for-high-school-students",
    "page": 31,
    "confidence": "high"
  },
  {
    "entity": "United States",
    "status": "entity",
    "excluded_reason": "Null",
    "category": "country",
    "role_in_text": "country",
    "technology_area": "unknown",
    "occurrence_sentence": "Country* Select Country United Kingdom United States",
    "source_document": "https://thequantuminsider.com/2020/06/09/fermilab-scientists-publish-quantum-computing-course-for-high-school-students",
    "page": 31
  },
  {
    "entity": "United Kingdom",
    "status": "entity",
    "excluded_reason": "Null",
    "category": "country",
    "role_in_text": "country",
    "technology_area": "unknown",
    "occurrence_sentence": "Virgin Islands Uganda Ukraine (Україна) United Arab Emirates (‫الإمارات العربية المتحدة‬‎) United Kingdom United States Uruguay Uzbekistan (Oʻzbekiston) Vanuatu Vatican City (Città del Vaticano) Venezuela Vietnam (Việt Nam) Wallis and Futuna Yemen (‫اليمن‬‎) Zambia Zimbabwe",
    "source_document": "https://thequantuminsider.com/2020/06/09/fermilab-scientists-publish-quantum-computing-course-for-high-school-students",
    "page": 32,
    "confidence": "high"
  },
  {
    "entity": "United States",
    "status": "entity",
    "excluded_reason": "Null",
    "category": "country",
    "role_in_text": "country",
    "technology_area": "unknown",
    "source_document": "https://thequantuminsider.com/2020/06/09/fermilab-scientists-publish-quantum-computing-course-for-high-school-students",
    "page": 32
  },
  {
    "entity": "Fermilab",
    "status": "entity",
    "excluded_reason": "Null",
    "category": "research institutes",
    "role_in_text": "publishes quantum computing course",
    "technology_area": "quantum computing",
    "occurrence_sentence": "Fermilab scientists publish quantum computing course for high school students",
    "source_document": "https://thequantuminsider.com/2020/06/09/fermilab-scientists-publish-quantum-computing-course-for-high-school-students",
    "page": 33,
    "confidence": "high"
  },
  {
    "entity": "Afghanistan (‫افغانستان‬‎)",
    "status": "entity",
    "excluded_reason": "Null",
    "category": "country",
    "role_in_text": "country",
    "technology_area": "unknown",
    "occurrence_sentence": "Afghanistan (‫افغانستان‬‎) Albania (Shqipëri) Algeria (‫الجزائر‬‎) American Samoa Andorra Angola Anguilla Antigua and Barbuda Argentina Armenia (Հայաստան) Aruba Australia Austria (Österreich) Azerbaijan (Azərbaycan) Bahamas Bahrain (‫البحرين‬‎) Bangladesh (বাংলাদেশ) Barbados Belarus (Беларусь) Belgium (België) Belize Benin (Bénin) Bermuda Bhutan (འབྲུག) Bolivia Bosnia and Herzegovina (Босна и Херцеговина) Botswana Brazil (Brasil) British Indian Ocean Territory British Virgin Islands Brunei Bulgaria (България) Burkina Faso Burundi (Uburundi) Cambodia (កម្ពុជា) Cameroon (Cameroun) Canada Cape Verde",
    "source_document": "https://thequantuminsider.com/2020/06/09/fermilab-scientists-publish-quantum-computing-course-for-high-school-students",
    "page": 34
  },
  {
    "entity": "Faroe Islands (Føroyar)",
    "status": "not_actor",
    "excluded_reason": "location_only",
    "category": "Null",
    "role_in_text": "Null",
    "technology_area": "Null",
    "occurrence_sentence": "Faroe Islands (Føroyar) Fiji Finland (Suomi) France French Guiana (Guyane française) French Polynesia (Polynésie française) Gabon Gambia Georgia (საქართველო) Germany (Deutschland) Ghana (Gaana) Gibraltar Greece (Ελλάδα) Greenland (Kalaallit Nunaat) Grenada Guadeloupe Guam Guatemala Guinea (Guinée) Guinea-Bissau (Guiné Bissau) Guyana Haiti Honduras Hong Kong (香港) Hungary (Magyarország) Iceland (Ísland) India (भारत) Indonesia Iran (‫ایران‬‎) Iraq (‫العراق‬‎) Ireland Israel (‫ישראל‬‎) Italy (Italia) Jamaica Japan (日本) Jordan (‫الأردن‬‎) Kazakhstan (Казахстан) Kenya Kiribati Kosovo Kuwait (‫الكويت‬‎) Kyrgyz",
    "source_document": "https://thequantuminsider.com/2020/06/09/fermilab-scientists-publish-quantum-computing-course-for-high-school-students",
    "page": 35
  },
  {
    "entity": "United Kingdom",
    "status": "entity",
    "excluded_reason": "Null",
    "category": "country",
    "role_in_text": "country",
    "technology_area": "unknown",
    "occurrence_sentence": "Select Country United Kingdom United States",
    "source_document": "https://thequantuminsider.com/2020/06/09/fermilab-scientists-publish-quantum-computing-course-for-high-school-students",
    "page": 36,
    "confidence": "high"
  },
  {
    "entity": "United States",
    "status": "entity",
    "excluded_reason": "Null",
    "category": "country",
    "role_in_text": "country",
    "technology_area": "unknown",
    "occurrence_sentence": "Select Country United Kingdom United States",
    "source_document": "https://thequantuminsider.com/2020/06/09/fermilab-scientists-publish-quantum-computing-course-for-high-school-students",
    "page": 36
  },
  {
    "entity": "United Kingdom",
    "status": "entity",
    "excluded_reason": "Null",
    "category": "country",
    "role_in_text": "country",
    "technology_area": "unknown",
    "occurrence_sentence": "Virgin Islands Uganda Ukraine (Україна) United Arab Emirates (‫الإمارات العربية المتحدة‬‎) United Kingdom United States Uruguay Uzbekistan (Oʻzbekiston) Vanuatu Vatican City (Città del Vaticano) Venezuela Vietnam (Việt Nam) Wallis and Futuna Yemen (‫اليمن‬‎) Zambia Zimbabwe",
    "source_document": "https://thequantuminsider.com/2020/06/09/fermilab-scientists-publish-quantum-computing-course-for-high-school-students",
    "page": 37,
    "confidence": "high"
  },
  {
    "entity": "United States",
    "status": "entity",
    "excluded_reason": "Null",
    "category": "country",
    "role_in_text": "country",
    "technology_area": "unknown",
    "source_document": "https://thequantuminsider.com/2020/06/09/fermilab-scientists-publish-quantum-computing-course-for-high-school-students",
    "page": 37
  },
  {
    "entity": "Fermilab",
    "status": "entity",
    "excluded_reason": "Null",
    "category": "research institutes",
    "role_in_text": "publishes quantum computing course",
    "technology_area": "quantum computing",
    "occurrence_sentence": "Fermilab scientists publish quantum computing course for high school students",
    "source_document": "https://thequantuminsider.com/2020/06/09/fermilab-scientists-publish-quantum-computing-course-for-high-school-students",
    "page": 38,
    "confidence": "high"
  },
  {
    "entity": "Hungary",
    "status": "entity",
    "excluded_reason": "Null",
    "category": "country",
    "role_in_text": "listed as a country",
    "technology_area": "unknown",
    "occurrence_sentence": "g Hungary Iceland India Indonesia Iran Iraq Ireland Isle of Man Israel Italy Jamaica Japan Jersey Jordan Kazakhstan Kenya Kiribati Kosovo Kuwait Kyrgyzstan Laos Latvia Lebanon Lesotho Liberia Libya Liechtenstein Lithuania Luxembourg Macau Macedonia (",
    "source_document": "https://thequantuminsider.com/2020/06/09/fermilab-scientists-publish-quantum-computing-course-for-high-school-students",
    "page": 38
  }
]